quiz_correcter/__init__.py
quiz_correcter/__main__.py
quiz_correcter/colorbox.py
quiz_correcter-0.1.0.dist-info/LICENSE
quiz_correcter-0.1.0.dist-info/METADATA
quiz_correcter-0.1.0.dist-info/WHEEL
quiz_correcter-0.1.0.dist-info/entry_points.txt
quiz_correcter-0.1.0.dist-info/RECORD
