Metadata-Version: 2.1
Name: quiz-correcter
Version: 0.1.0
Summary: 
Home-page: https://github.com/violatimon/quiz_correcter
License: MIT
Author: Timon Viola
Author-email: 44016238+timonviola@users.noreply.github.com
Requires-Python: >=3.12,<4.0
Classifier: Development Status :: 4 - Beta
Classifier: Environment :: Console
Classifier: Intended Audience :: Private
Classifier: License :: OSI Approved :: MIT License
Classifier: Operating System :: MacOS
Classifier: Operating System :: POSIX :: Linux
Classifier: Programming Language :: Python :: 3
Classifier: Programming Language :: Python :: 3.10
Classifier: Programming Language :: Python :: 3.11
Classifier: Programming Language :: Python :: 3.12
Classifier: Typing :: Typed
Requires-Dist: rich-click (>=1.8.2,<2.0.0)
